pep440nz/__init__.py
pep440nz/__version__.py
pep440nz/git.py
pep440nz/version.py
pep440nz-0.5.2.data/data/requirements.txt
pep440nz-0.5.2.dist-info/METADATA
pep440nz-0.5.2.dist-info/WHEEL
pep440nz-0.5.2.dist-info/entry_points.txt
pep440nz-0.5.2.dist-info/top_level.txt
pep440nz-0.5.2.dist-info/RECORD
