Metadata-Version: 2.1
Name: pep440nz
Version: 0.5.2
Summary: PEP440-like version management
Home-page: UNKNOWN
Author: Clement
Author-email: neze+pypi@melix.org
License: UNKNOWN
Platform: UNKNOWN
Classifier: Programming Language :: Python :: 3
